{
  "primary": {
    "DEFAULT": "#532565",
    "vivid": "#561e6c",
    "min": "#08040a",
    "darkest": "#1b0c21",
    "darker": "#2e1438",
    "dark": "#401d4e",
    "light": "#7a5688",
    "lighter": "#a087aa",
    "lightest": "#c7b8cd",
    "max": "#eee9f0"
  },
  "primary-contrast": {
    "DEFAULT": "#fefefe",
    "vivid": "#fefefe",
    "min": "#fefefe",
    "darkest": "#fefefe",
    "darker": "#fefefe",
    "dark": "#fefefe",
    "light": "#fefefe",
    "lighter": "#111111",
    "lightest": "#111111",
    "max": "#111111"
  },
  "secondary": {
    "DEFAULT": "#982568",
    "vivid": "#a11c6a",
    "min": "#0f040a",
    "darkest": "#310c22",
    "darker": "#541439",
    "dark": "#761d51",
    "light": "#af568a",
    "lighter": "#c687ac",
    "lightest": "#deb8ce",
    "max": "#f5e9f0"
  },
  "secondary-contrast": {
    "DEFAULT": "#fefefe",
    "vivid": "#fefefe",
    "min": "#fefefe",
    "darkest": "#fefefe",
    "darker": "#fefefe",
    "dark": "#fefefe",
    "light": "#fefefe",
    "lighter": "#111111",
    "lightest": "#111111",
    "max": "#111111"
  },
  "accent": {
    "DEFAULT": "#982568",
    "vivid": "#a11c6a",
    "min": "#0f040a",
    "darkest": "#310c22",
    "darker": "#541439",
    "dark": "#761d51",
    "light": "#af568a",
    "lighter": "#c687ac",
    "lightest": "#deb8ce",
    "max": "#f5e9f0"
  },
  "accent-contrast": {
    "DEFAULT": "#111111",
    "vivid": "#111111",
    "min": "#fefefe",
    "darkest": "#fefefe",
    "darker": "#fefefe",
    "dark": "#fefefe",
    "light": "#111111",
    "lighter": "#111111",
    "lightest": "#111111",
    "max": "#111111"
  },
  "base": {
    "DEFAULT": "#982568",
    "vivid": "#a11c6a",
    "min": "#0f040a",
    "darkest": "#310c22",
    "darker": "#541439",
    "dark": "#761d51",
    "light": "#af568a",
    "lighter": "#c687ac",
    "lightest": "#deb8ce",
    "max": "#f5e9f0"
  },
  "base-contrast": {
    "DEFAULT": "#111111",
    "vivid": "#111111",
    "min": "#fefefe",
    "darkest": "#fefefe",
    "darker": "#111111",
    "dark": "#111111",
    "light": "#111111",
    "lighter": "#111111",
    "lightest": "#111111",
    "max": "#111111"
  }
}
