{
  "navigation": {
    "classNames": {
      "root": "pl-1 mr-6 bg-base-max text-primary opacity-100 hover:opacity-100",
      "item": "py-2 px-4 hover:bg-base-lightest hover:text-base-contrast",
      "navigationPanel": "bg-base-max text-primary"
    },
    "logo": {
      "src": "/images/brh/logo.png",
      "height": 256,
      "width": 320,
      "href": "/Discovery"
    },
    "items": [
      {
        "icon": "gen3:query",
        "href": "/Discovery",
        "name": "Discovery",
        "tooltip": "Use free-text search and tags to rapidly find relevant studies, discover new datasets across multiple resources, and easily export selected data files to the analysis workspace."
      },]]]
      {
        "name": "Notebooks",
        "href": "/NotebookLite",
        "icon": "gen3:notebook",
        "tooltip": "Notebooks for basic analysis"
      },
      {
        "icon": "gen3:profile",
        "href": "/Profile",
        "name": "Profile",
        "tooltip": "Create API keys for programmatic data access, and review your authorization privileges to datasets and services."
      }
    ]
  },
  "topBar": {
    "items": [
      {
        "link": "https://uc-cdis.github.io/BRH-documentation/",
        "name": "Documentation",
        "classNames": {
          "root": "border-base-light",
          "label": "text-white",
          "button": "hover:border-white"
        }
      },
      {
        "link": "brhsupport@datacommons.io",
        "name": "Email Support",
        "classNames": {
          "root": "border-base-light",
          "label": "text-white",
          "button": "hover:border-white"
        }
      },
      {
        "link": "https://uc-cdis.github.io/platform-citation/brh-cite/",
        "name": "Cite BRH",
        "classNames": {
          "root": "border-base-light",
          "label": "text-white",
          "button": "hover:border-white"
        }
      }
    ],
    "loginButtonVisibility": "visible",
    "classNames": {
      "root": "border-base-light text-primary-contrast-dark",
      "label": "text-primary-contrast",
      "button": "hover:border-white"
    }
  }
}
